coven.py
setup.cfg
setup.py
coven.egg-info/PKG-INFO
coven.egg-info/SOURCES.txt
coven.egg-info/dependency_links.txt
coven.egg-info/entry_points.txt
coven.egg-info/requires.txt
coven.egg-info/top_level.txt