Metadata-Version: 1.1
Name: coven
Version: 0.0.0
Summary: Coven is a code coverage tracing harness.
Home-page: https://github.com/gwk/coven
Author: George King
Author-email: george.w.king@gmail.com
License: CC0
Keywords: testing
Platform: UNKNOWN
Classifier: Development Status :: 4 - Beta
Classifier: Environment :: Console
Classifier: Intended Audience :: Developers
Classifier: License :: CC0 1.0 Universal (CC0 1.0) Public Domain Dedication
Classifier: Programming Language :: Python :: 3 :: Only
Classifier: Topic :: Software Development :: Testing
